sequential/seq/mux.v
`timescale 1ns / 1ps

module mux2to1 (
    output [63:0] Y,  // Output
    input  [63:0] A,  // Input 0
    input  [63:0] B,  // Input 1
    input         S   // Select
);
    // When S=0, Y=A; when S=1, Y=B
    assign Y = S ? B : A;
endmodule

pipelined/fetch.v
`timescale 1ns / 1ps
`include "mux.v"

module fetch (
    input         clk,
    input  [63:0] PC,        // Program Counter
    input  [31:0] instr,     // 32-bit instruction
    input         branch_taken, // Control signal indicating branch/jump should be taken
    input  [63:0] branch_target, // Target address for branch/jump

    // Decoded instruction fields
    output [6:0]  opcode,  
    output [4:0]  rd, rs1, rs2,  
    output [2:0]  funct3,  
    output [6:0]  funct7,  
    output [63:0] imm,  // Immediate Value
    output [63:0] nextp,  // Next PC

    // Control Signals
    output instr_valid, imem_error  
);

    // Extract opcode and rs1 (always valid)
    assign opcode = instr[6:0];
    assign rs1    = instr[19:15];

    // Internal signal for immediate value
    reg [63:0] imm_internal;

    // Default values for invalid fields
    reg [4:0] rd_internal, rs2_internal;
    reg [2:0] funct3_internal;
    reg [6:0] funct7_internal;

    always @(*) begin
        // Default invalid values
        rd_internal   = 5'b00000;
        rs2_internal  = 5'b00000;
        funct3_internal = 3'b000;
        funct7_internal = 7'b0000000;
        imm_internal  = 64'b0;

        case (opcode)
            7'b0110011: begin // R-type (e.g., add, sub)
                rd_internal    = instr[11:7];
                rs2_internal   = instr[24:20];
                funct3_internal = instr[14:12];
                funct7_internal = instr[31:25];
            end

            7'b0010011, // I-type (e.g., addi, andi, ori)
            7'b0000011: begin // Load (lw)
                rd_internal    = instr[11:7];
                funct3_internal = instr[14:12];
                imm_internal   = {{52{instr[31]}}, instr[31:20]};
            end
            
            7'b0100011: begin // S-type (e.g., sw, sh, sb)
                rs2_internal   = instr[24:20];
                funct3_internal = instr[14:12];
                imm_internal   = {{52{instr[31]}}, instr[31:25], instr[11:7]};
            end

            7'b1100011: begin // S B-type (e.g., beq, bne)
                rs2_internal   = instr[24:20];
                funct3_internal = instr[14:12];
                imm_internal   = {{51{instr[31]}}, instr[31], instr[7], instr[30:25], instr[11:8], 1'b0};
            end

            7'b0110111, // U-type (lui) Loads a 20-bit immediate into the upper 20 bits of rd, setting the lower 12 bits to zero.
            7'b0010111: begin // U-type (auipc) AUIPC (Add Upper Immediate to PC) Computes PC + (imm << 12) and stores the result in rd
                rd_internal    = instr[11:7];
                imm_internal   = {{32{instr[31]}}, instr[31:12], 12'b0};
            end

            7'b1101111: begin // UJ-type (jal)
                rd_internal    = instr[11:7];
                imm_internal   = {{43{instr[31]}}, instr[31], instr[19:12], instr[20], instr[30:21], 1'b0};
            end
        endcase
    end

    assign rd     = rd_internal;
    assign rs2    = rs2_internal;
    assign funct3 = funct3_internal;
    assign funct7 = funct7_internal;
    assign imm    = imm_internal;

    // Calculate sequential next PC (PC+4)
    wire [63:0] sequential_pc;
assign sequential_pc = PC + 64'd4;
// assign branch_target = branch_target;
wire [63:0] branch_pc;
assign branch_pc = PC + branch_target;


    
    // Instantiate the 2-to-1 MUX for PC selection
    mux2to1 pc_mux (
        .Y(nextp),             // Output
        .A(sequential_pc),     // PC+4 (when S=0)
        .B(branch_pc),     // Branch target (when S=1)
        .S(branch_taken)       // Select signal
    );
    
    // Instruction validity check (basic check for known opcodes)
    assign instr_valid = (opcode == 7'b0110011) || // R-type (add, sub)
                         (opcode == 7'b0010011) || // I-type (addi, andi, ori)
                         (opcode == 7'b0000011) || // Load (lw)
                         (opcode == 7'b0100011) || // Store (sw)
                         (opcode == 7'b1100011) ;

    // Memory access error check (assuming a 1024-byte instruction memory)
    assign imem_error = (PC >= 1024) ? 1'b1 : 1'b0;

endmodule

sequential/seq/fetch_tb.v
`timescale 1ns / 1ps

module fetch_tb;
    // Inputs
    reg         clk;
    reg  [63:0] PC;
    reg  [31:0] instr;
    reg         branch_taken;
    reg  [63:0] branch_target;

    // Outputs
    wire [6:0]  opcode;
    wire [4:0]  rd, rs1, rs2;
    wire [2:0]  funct3;
    wire [6:0]  funct7;
    wire [63:0] imm;
    wire [63:0] nextp;
    wire        instr_valid, imem_error;
    
    // Instantiate the Unit Under Test (UUT)
    fetch uut (
        .clk(clk),
        .PC(PC),
        .instr(instr),
        .branch_taken(branch_taken),
        .branch_target(branch_target),
        .opcode(opcode),
        .rd(rd),
        .rs1(rs1),
        .rs2(rs2),
        .funct3(funct3),
        .funct7(funct7),
        .imm(imm),
        .nextp(nextp),
        .instr_valid(instr_valid),
        .imem_error(imem_error)
    );
    
    // Define clock
    always #5 clk = ~clk;
    
    // Test case helper task
    task test_instruction;
        input [63:0] pc_val;
        input [31:0] instruction;
        input [8*20:1] instr_name;     // Character array to store the instruction name
        input [63:0] expected_imm;     // Expected immediate value
        input branch_taken_val;        // Add branch_taken input
        input [63:0] branch_target_val; // Add branch_target input
        begin
            PC = pc_val;
            instr = instruction;
            branch_taken = branch_taken_val;       // Set branch_taken
            branch_target = branch_target_val;     // Set branch_target
            #10; // Wait for combinational logic to settle
            $display("\n========== %s ==========\n", instr_name);
            $display("PC = %b(%d), Instr = %b(%d)\n", PC, PC, instr, instr);
            $display("branch_taken = %b, branch_target = %d", branch_taken, branch_target);
            $display("Decoded fields:");
            $display("  opcode = %b (%d)", opcode, opcode);
            $display("  rd     = %b (%d)", rd, rd);
            $display("  rs1    = %b (%d)", rs1, rs1);
            $display("  rs2    = %b (%d)", rs2, rs2);
            $display("  funct3 = %b (%d)", funct3, funct3);
            $display("  funct7 = %b (%d)", funct7, funct7);
            
            // Display and verify the immediate value
            $display("  imm    = %b (%d) (Expected: %b (%d))", imm, imm, expected_imm, expected_imm);
            if (imm !== expected_imm) begin
                $display("  *** ERROR: Immediate value mismatch! ***");
            end
            $display("  nextp  = %b(%d)", nextp,nextp);
            $display("  instr_valid = %b, imem_error = %b", instr_valid, imem_error);
        end
    endtask
    
    // Test Vector Generation
    initial begin
        // Initialize inputs
        clk = 0;
        PC = 64'h0;
        instr = 32'h0;
        branch_taken = 0;      // Initialize branch_taken
        branch_target = 64'h0; // Initialize branch_target
        
        // Wait for global reset
        #100;
        
        // Test Cases with branch values (branch_taken=0 for regular instruction flow)
        // ADD x3, x1, x2 (R-type, no immediate)
        test_instruction(64'h0000, 32'h002081B3, "ADD x3, x1, x2", 64'h0, 0, 64'h0); 
        
        // SUB x3, x1, x2 (R-type, no immediate)
        test_instruction(64'h0004, 32'h402081B3, "SUB x3, x1, x2", 64'h0, 0, 64'h0); 
        
        // AND x3, x1, x2 (R-type, no immediate)
        test_instruction(64'h0008, 32'h0020F1B3, "AND x3, x1, x2", 64'h0, 0, 64'h0); 
        
        // OR x3, x1, x2 (R-type, no immediate)
        test_instruction(64'h000C, 32'h0020E1B3, "OR x3, x1, x2", 64'h0, 0, 64'h0); 
        
        // LD x2, 8(x1) (I-type load, immediate 8)
        test_instruction(64'h0010, 32'h0080B103, "LD x2, 8(x1)", 64'h8, 0, 64'h0); 
        
        // SD x2, 16(x1) (S-type store, immediate 16)
        test_instruction(64'h0014, 32'h0020B823, "SD x2, 16(x1)", 64'h10, 0, 64'h0); 
        
        // BEQ x1, x2, 32 (B-type branch, immediate 32) - test with branch not taken
        test_instruction(64'h0018, 32'h02208063, "BEQ x1, x2, 32 (not taken)", 64'h20, 0, 64'h0); 
        
        // BEQ x1, x2, 32 (B-type branch, immediate 32) - test with branch taken
        test_instruction(64'h0018, 32'h02208063, "BEQ x1, x2, 32 (taken)", 64'h20, 1, 64'h0038); 
        
        // Additional test cases
        test_instruction(64'h0000, 32'h00208433, "ADD x8, x1, x2", 64'h0, 0, 64'h0);               // R-type
        test_instruction(64'h0004, 32'h02A00093, "ADDI x1, x0, 42", 64'h2A, 0, 64'h0);             // I-type
        test_instruction(64'h0008, 32'hFD600093, "ADDI x1, x0, -42", 64'hFFFFFFFFFFFFFFD6, 0, 64'h0); // Negative immediate
        test_instruction(64'h000C, 32'h0080B103, "LD x2, 8(x1)", 64'h8, 0, 64'h0);                 // Load Doubleword
        test_instruction(64'h0010, 32'h0020B823, "SD x2, 16(x1)", 64'h10, 0, 64'h0);               // Store Doubleword
        
        // Branch tests with taking branch or not
        test_instruction(64'h0014, 32'h02208063, "BEQ x1, x2, 32", 64'h20, 0, 64'h0);              // Branch not taken
        test_instruction(64'h0014, 32'h02208063, "BEQ x1, x2, 32 (taken)", 64'h20, 1, 64'h0034);   // Branch taken
        test_instruction(64'h0018, 32'hFE208063, "BEQ x1, x2, -32", 64'hFFFFFFFFFFFFFFE0, 0, 64'h0); // Negative offset not taken
        test_instruction(64'h0018, 32'hFE208063, "BEQ x1, x2, -32 (taken)", 64'hFFFFFFFFFFFFFFE0, 1, 64'hFFF8); // Negative offset taken
        
        // Jump tests
        test_instruction(64'h001C, 32'h08000867, "JAL x1, 128", 64'h80, 0, 64'h0);                 // Jump not taken
        test_instruction(64'h001C, 32'h08000867, "JAL x1, 128 (taken)", 64'h80, 1, 64'h009C);      // Jump taken
        test_instruction(64'h0020, 32'hF8000867, "JAL x1, -128", 64'hFFFFFFFFFFFFFF80, 0, 64'h0);  // Negative jump not taken
        test_instruction(64'h0020, 32'hF8000867, "JAL x1, -128 (taken)", 64'hFFFFFFFFFFFFFF80, 1, 64'hFFFFFFFFFFFFFFB0); // Negative jump taken
        
        // Other instruction types
        test_instruction(64'h0024, 32'h123450B7, "LUI x1, 0x12345", 64'h0000000012345000, 0, 64'h0); // LUI
        test_instruction(64'h0028, 32'h12345117, "AUIPC x2, 0x12345", 64'h0000000012345000, 0, 64'h0); // AUIPC
        test_instruction(64'h002C, 32'h12345678, "Invalid Opcode", 64'h0, 0, 64'h0);              // Invalid opcode
        test_instruction(64'h1000, 32'h00000013, "Memory Error Check", 64'h0, 0, 64'h0);          // Memory error
        
        $display("\n========== All tests completed ==========");
        $finish;
    end
    
    // VCD file for waveform analysis
    initial begin
        $dumpfile("fetch_tb.vcd");
        $dumpvars(0, fetch_tb);
    end
    
endmodule

pipelined/fetch_tb.vcd
$date
	Sat Mar  8 03:00:16 2025
$end
$version
	Icarus Verilog
$end
$timescale
	1ps
$end
$scope module fetch_tb $end
$var wire 5 ! rs2 [4:0] $end
$var wire 5 " rs1 [4:0] $end
$var wire 5 # rd [4:0] $end
$var wire 7 $ opcode [6:0] $end
$var wire 64 % nextp [63:0] $end
$var wire 1 & instr_valid $end
$var wire 64 ' imm [63:0] $end
$var wire 1 ( imem_error $end
$var wire 7 ) funct7 [6:0] $end
$var wire 3 * funct3 [2:0] $end
$var reg 64 + PC [63:0] $end
$var reg 1 , branch_taken $end
$var reg 64 - branch_target [63:0] $end
$var reg 1 . clk $end
$var reg 32 / instr [31:0] $end
$scope module uut $end
$var wire 64 0 PC [63:0] $end
$var wire 1 , branch_taken $end
$var wire 64 1 branch_target [63:0] $end
$var wire 1 . clk $end
$var wire 3 2 funct3 [2:0] $end
$var wire 7 3 funct7 [6:0] $end
$var wire 64 4 imm [63:0] $end
$var wire 32 5 instr [31:0] $end
$var wire 1 & instr_valid $end
$var wire 5 6 rd [4:0] $end
$var wire 5 7 rs2 [4:0] $end
$var wire 64 8 sequential_pc [63:0] $end
$var wire 5 9 rs1 [4:0] $end
$var wire 7 : opcode [6:0] $end
$var wire 64 ; nextp [63:0] $end
$var wire 1 ( imem_error $end
$var wire 64 < branch_pc [63:0] $end
$var reg 3 = funct3_internal [2:0] $end
$var reg 7 > funct7_internal [6:0] $end
$var reg 64 ? imm_internal [63:0] $end
$var reg 5 @ rd_internal [4:0] $end
$var reg 5 A rs2_internal [4:0] $end
$scope module pc_mux $end
$var wire 64 B A [63:0] $end
$var wire 64 C B [63:0] $end
$var wire 1 , S $end
$var wire 64 D Y [63:0] $end
$upscope $end
$upscope $end
$scope task test_instruction $end
$var reg 1 E branch_taken_val $end
$var reg 64 F branch_target_val [63:0] $end
$var reg 64 G expected_imm [63:0] $end
$var reg 160 H instr_name [160:1] $end
$var reg 32 I instruction [31:0] $end
$var reg 64 J pc_val [63:0] $end
$upscope $end
$upscope $end
$enddefinitions $end
#0
$dumpvars
bx J
bx I
bx H
bx G
bx F
xE
b100 D
b0 C
b100 B
b0 A
b0 @
b0 ?
b0 >
b0 =
b0 <
b100 ;
b0 :
b0 9
b100 8
b0 7
b0 6
b0 5
b0 4
b0 3
b0 2
b0 1
b0 0
b0 /
0.
b0 -
0,
b0 +
b0 *
b0 )
0(
b0 '
0&
b100 %
b0 $
b0 #
b0 "
b0 !
$end
#5000
1.
#10000
0.
#15000
1.
#20000
0.
#25000
1.
#30000
0.
#35000
1.
#40000
0.
#45000
1.
#50000
0.
#55000
1.
#60000
0.
#65000
1.
#70000
0.
#75000
1.
#80000
0.
#85000
1.
#90000
0.
#95000
1.
#100000
1&
b10 !
b10 7
b10 A
b11 #
b11 6
b11 @
b110011 $
b110011 :
b1 "
b1 9
0.
b1000001000000110110011 /
b1000001000000110110011 5
b0 F
0E
b0 G
b100000101000100010001000010000001111000001100110010110000100000011110000011000100101100001000000111100000110010 H
b1000001000000110110011 I
b0 J
#105000
1.
#110000
b100000 )
b100000 3
b100000 >
b10 !
b10 7
b10 A
b11 #
b11 6
b11 @
b1000 %
b1000 ;
b1000 D
0.
b1000000001000001000000110110011 /
b1000000001000001000000110110011 5
b1000 8
b1000 B
b100 <
b100 C
b100 +
b100 0
b101001101010101010000100010000001111000001100110010110000100000011110000011000100101100001000000111100000110010 H
b1000000001000001000000110110011 I
b100 J
#115000
1.
#120000
b111 *
b111 2
b111 =
b0 )
b0 3
b0 >
b10 !
b10 7
b10 A
b11 #
b11 6
b11 @
b1100 %
b1100 ;
b1100 D
0.
b1000001111000110110011 /
b1000001111000110110011 5
b1100 8
b1100 B
b1000 <
b1000 C
b1000 +
b1000 0
b100000101001110010001000010000001111000001100110010110000100000011110000011000100101100001000000111100000110010 H
b1000001111000110110011 I
b1000 J
#125000
1.
#130000
b110 *
b110 2
b110 =
b10 !
b10 7
b10 A
b11 #
b11 6
b11 @
b10000 %
b10000 ;
b10000 D
0.
b1000001110000110110011 /
b1000001110000110110011 5
b10000 8
b10000 B
b1100 <
b1100 C
b1100 +
b1100 0
b1001111010100100010000001111000001100110010110000100000011110000011000100101100001000000111100000110010 H
b1000001110000110110011 I
b1100 J
#135000
1.
#140000
b1000 '
b1000 4
b1000 ?
b11 *
b11 2
b11 =
b0 !
b0 7
b0 A
b10 #
b10 6
b10 @
b11 $
b11 :
b10100 %
b10100 ;
b10100 D
0.
b100000001011000100000011 /
b100000001011000100000011 5
b10100 8
b10100 B
b10000 <
b10000 C
b10000 +
b10000 0
b1000 G
b10011000100010000100000011110000011001000101100001000000011100000101000011110000011000100101001 H
b100000001011000100000011 I
b10000 J
#145000
1.
#150000
b10 !
b10 7
b10 A
b10000 '
b10000 4
b10000 ?
b11 *
b11 2
b11 =
b0 #
b0 6
b0 @
b100011 $
b100011 :
b11000 %
b11000 ;
b11000 D
0.
b1000001011100000100011 /
b1000001011100000100011 5
b11000 8
b11000 B
b10100 <
b10100 C
b10100 +
b10100 0
b10000 G
b1010011010001000010000001111000001100100010110000100000001100010011011000101000011110000011000100101001 H
b1000001011100000100011 I
b10100 J
#155000
1.
#160000
b10000 '
b10000 4
b10000 ?
b0 *
b0 2
b0 =
b10 !
b10 7
b10 A
b1100011 $
b1100011 :
b11100 %
b11100 ;
b11100 D
0.
b10001000001000000001100011 /
b10001000001000000001100011 5
b11100 8
b11100 B
b11000 <
b11000 C
b11000 +
b11000 0
b100000 G
b10110000100000011110000011001000101100001000000011001100110010001000000010100001101110011011110111010000100000011101000110000101101011011001010110111000101001 H
b10001000001000000001100011 I
b11000 J
#165000
1.
#170000
b1010000 %
b1010000 ;
b1010000 D
0.
b1010000 <
b1010000 C
b111000 -
b111000 1
1,
b111000 F
1E
b101000100100000011110000011000100101100001000000111100000110010001011000010000000110011001100100010000000101000011101000110000101101011011001010110111000101001 H
#175000
1.
#180000
1&
b1000 #
b1000 6
b1000 @
b0 '
b0 4
b0 ?
b10 !
b10 7
b10 A
b110011 $
b110011 :
b100 %
b100 ;
b100 D
0.
b0 -
b0 1
0,
b1000001000010000110011 /
b1000001000010000110011 5
b100 8
b100 B
b0 <
b0 C
b0 +
b0 0
b0 F
0E
b0 G
b100000101000100010001000010000001111000001110000010110000100000011110000011000100101100001000000111100000110010 H
b1000001000010000110011 I
b0 J
#185000
1.
#190000
b101010 '
b101010 4
b101010 ?
b0 !
b0 7
b0 A
b1 #
b1 6
b1 @
b10011 $
b10011 :
b0 "
b0 9
b1000 %
b1000 ;
b1000 D
0.
b10101000000000000010010011 /
b10101000000000000010010011 5
b1000 8
b1000 B
b100 <
b100 C
b100 +
b100 0
b101010 G
b10000010100010001000100010010010010000001111000001100010010110000100000011110000011000000101100001000000011010000110010 H
b10101000000000000010010011 I
b100 J
#195000
1.
#200000
b1111111111111111111111111111111111111111111111111111111111010110 '
b1111111111111111111111111111111111111111111111111111111111010110 4
b1111111111111111111111111111111111111111111111111111111111010110 ?
b1 #
b1 6
b1 @
b1100 %
b1100 ;
b1100 D
0.
b11111101011000000000000010010011 /
b11111101011000000000000010010011 5
b1100 8
b1100 B
b1000 <
b1000 C
b1000 +
b1000 0
b1111111111111111111111111111111111111111111111111111111111010110 G
b1000001010001000100010001001001001000000111100000110001001011000010000001111000001100000010110000100000001011010011010000110010 H
b11111101011000000000000010010011 I
b1000 J
#205000
1.
#210000
b11 *
b11 2
b11 =
b1000 '
b1000 4
b1000 ?
b10 #
b10 6
b10 @
b11 $
b11 :
b1 "
b1 9
b10000 %
b10000 ;
b10000 D
0.
b100000001011000100000011 /
b100000001011000100000011 5
b10000 8
b10000 B
b1100 <
b1100 C
b1100 +
b1100 0
b1000 G
b10011000100010000100000011110000011001000101100001000000011100000101000011110000011000100101001 H
b100000001011000100000011 I
b1100 J
#215000
1.
#220000
b10 !
b10 7
b10 A
b10000 '
b10000 4
b10000 ?
b11 *
b11 2
b11 =
b0 #
b0 6
b0 @
b100011 $
b100011 :
b10100 %
b10100 ;
b10100 D
0.
b1000001011100000100011 /
b1000001011100000100011 5
b10100 8
b10100 B
b10000 <
b10000 C
b10000 +
b10000 0
b10000 G
b1010011010001000010000001111000001100100010110000100000001100010011011000101000011110000011000100101001 H
b1000001011100000100011 I
b10000 J
#225000
1.
#230000
b10000 '
b10000 4
b10000 ?
b0 *
b0 2
b0 =
b10 !
b10 7
b10 A
b1100011 $
b1100011 :
b11000 %
b11000 ;
b11000 D
0.
b10001000001000000001100011 /
b10001000001000000001100011 5
b11000 8
b11000 B
b10100 <
b10100 C
b10100 +
b10100 0
b100000 G
b100001001000101010100010010000001111000001100010010110000100000011110000011001000101100001000000011001100110010 H
b10001000001000000001100011 I
b10100 J
#235000
1.
#240000
b1001000 %
b1001000 ;
b1001000 D
0.
b1001000 <
b1001000 C
b110100 -
b110100 1
1,
b110100 F
1E
b101000100100000011110000011000100101100001000000111100000110010001011000010000000110011001100100010000000101000011101000110000101101011011001010110111000101001 H
#245000
1.
#250000
b1111111111111111111111111111111111111111111111111111101111110000 '
b1111111111111111111111111111111111111111111111111111101111110000 4
b1111111111111111111111111111111111111111111111111111101111110000 ?
b10 !
b10 7
b10 A
b11100 %
b11100 ;
b11100 D
0.
b0 -
b0 1
0,
b11111110001000001000000001100011 /
b11111110001000001000000001100011 5
b11100 8
b11100 B
b11000 <
b11000 C
b11000 +
b11000 0
b0 F
0E
b1111111111111111111111111111111111111111111111111111111111100000 G
b10000100100010101010001001000000111100000110001001011000010000001111000001100100010110000100000001011010011001100110010 H
b11111110001000001000000001100011 I
b11000 J
#255000
1.
#260000
b10000000000010000 %
b10000000000010000 ;
b10000000000010000 D
0.
b10000000000010000 <
b10000000000010000 C
b1111111111111000 -
b1111111111111000 1
1,
b1111111111111000 F
1E
b10000001111000001100010010110000100000011110000011001000101100001000000010110100110011001100100010000000101000011101000110000101101011011001010110111000101001 H
#265000
1.
#270000
0&
b0 '
b0 4
b0 ?
b0 !
b0 7
b0 A
b1100111 $
b1100111 :
b0 "
b0 9
b100000 %
b100000 ;
b100000 D
0.
b0 -
b0 1
0,
b1000000000000000100001100111 /
b1000000000000000100001100111 5
b100000 8
b100000 B
b11100 <
b11100 C
b11100 +
b11100 0
b0 F
0E
b10000000 G
b100101001000001010011000010000001111000001100010010110000100000001100010011001000111000 H
b1000000000000000100001100111 I
b11100 J
#275000
1.
#280000
b10111000 %
b10111000 ;
b10111000 D
0.
b10111000 <
b10111000 C
b10011100 -
b10011100 1
1,
b10011100 F
1E
b1001010010000010100110000100000011110000011000100101100001000000011000100110010001110000010000000101000011101000110000101101011011001010110111000101001 H
#285000
1.
#290000
b100100 %
b100100 ;
b100100 D
0.
b0 -
b0 1
0,
b11111000000000000000100001100111 /
b11111000000000000000100001100111 5
b100100 8
b100100 B
b100000 <
b100000 C
b100000 +
b100000 0
b0 F
0E
b1111111111111111111111111111111111111111111111111111111110000000 G
b10010100100000101001100001000000111100000110001001011000010000000101101001100010011001000111000 H
b11111000000000000000100001100111 I
b100000 J
#295000
1.
#300000
b1111111111111111111111111111111111111111111111111111111111010000 %
b1111111111111111111111111111111111111111111111111111111111010000 ;
b1111111111111111111111111111111111111111111111111111111111010000 D
0.
b1111111111111111111111111111111111111111111111111111111111010000 <
b1111111111111111111111111111111111111111111111111111111111010000 C
b1111111111111111111111111111111111111111111111111111111110110000 -
b1111111111111111111111111111111111111111111111111111111110110000 1
1,
b1111111111111111111111111111111111111111111111111111111110110000 F
1E
b100101001000001010011000010000001111000001100010010110000100000001011010011000100110010001110000010000000101000011101000110000101101011011001010110111000101001 H
#305000
1.
#310000
1&
b10010001101000101000000000000 '
b10010001101000101000000000000 4
b10010001101000101000000000000 ?
b1 #
b1 6
b1 @
b110111 $
b110111 :
b1000 "
b1000 9
b101000 %
b101000 ;
b101000 D
0.
b0 -
b0 1
0,
b10010001101000101000010110111 /
b10010001101000101000010110111 5
b101000 8
b101000 B
b100100 <
b100100 C
b100100 +
b100100 0
b0 F
0E
b10010001101000101000000000000 G
b10011000101010101001001001000000111100000110001001011000010000000110000011110000011000100110010001100110011010000110101 H
b10010001101000101000010110111 I
b100100 J
#315000
1.
#320000
b10010001101000101000000000000 '
b10010001101000101000000000000 4
b10010001101000101000000000000 ?
b10 #
b10 6
b10 @
b10111 $
b10111 :
b101100 %
b101100 ;
b101100 D
0.
b10010001101000101000100010111 /
b10010001101000101000100010111 5
b101100 8
b101100 B
b101000 <
b101000 C
b101000 +
b101000 0
b100000101010101010010010101000001000011001000000111100000110010001011000010000000110000011110000011000100110010001100110011010000110101 H
b10010001101000101000100010111 I
b101000 J
#325000
1.
#330000
0&
b0 '
b0 4
b0 ?
b0 #
b0 6
b0 @
b1111000 $
b1111000 :
b110000 %
b110000 ;
b110000 D
0.
b10010001101000101011001111000 /
b10010001101000101011001111000 5
b110000 8
b110000 B
b101100 <
b101100 C
b101100 +
b101100 0
b0 G
b100100101101110011101100110000101101100011010010110010000100000010011110111000001100011011011110110010001100101 H
b10010001101000101011001111000 I
b101100 J
#335000
1.
#340000
1&
b10011 $
b10011 :
b0 "
b0 9
b1000000000100 %
b1000000000100 ;
b1000000000100 D
1(
0.
b10011 /
b10011 5
b1000000000100 8
b1000000000100 B
b1000000000000 <
b1000000000000 C
b1000000000000 +
b1000000000000 0
b10011010110010101101101011011110111001001111001001000000100010101110010011100100110111101110010001000000100001101101000011001010110001101101011 H
b10011 I
b1000000000000 J
