sequential/seq/alu.v
`timescale 1ns / 1ps


`include "adder.v"
`include "sub.v"
`include "and.v"
`include "or.v"
`include "xor.v"
`include "slt.v"
`include "sltu.v"
`include "sll.v"
`include "srl.v"
`include "sra.v"




module ALU (
    input [6:0] funct7,  
    input [2:0] funct3,  
    input [6:0] opcode,  
    input signed [63:0] A,       
    input signed [63:0] B, 
    input [11:0] addr,
   
    output reg signed [63:0] result,
    output reg carry_alu,
    output reg overflow_alu,
    output reg zero_flag
   
);





    wire [63:0] add_result, sub_result, and_result, or_result, xor_result;
    wire [63:0]  sll_result, srl_result, sra_result, mem_result;
    wire add_carry, add_overflow;
    wire sub_borrow, sub_overflow;
    wire [63:0] slt_result, sltu_result;
    wire add_err;
   
    wire carry_out, overflow_flag;
    wire [63:0] address;

wire carry_outi, overflow_flagi;
    wire [63:0] addressi;


    
    bit64_adder add_inst (.a(A), .b(B), .sum(add_result), .carry(add_carry), .overflow(add_overflow));
    bit64_subtractor sub_inst (.a(A), .b(B), .difference(sub_result), .borrow(sub_borrow),.overflow(sub_overflow));
    and_gate and_inst (.x(A), .y(B), .final(and_result));
    or_gate or_inst (.x(A), .y(B), .final(or_result));
    xor_gate xor_inst (.x(A), .y(B), .final(xor_result));
    compare_bitwise_64_signed slt_inst (.rs1(A), .rs2(B), .result(slt_result));
    compare_bitwise_64 sltu_inst (.rs1($unsigned(A)), .rs2($unsigned(B)), .result(sltu_result));
    shift_sll sll_inst (.a(A), .n(B[5:0]), .result(sll_result)); 
    shift_srl srl_inst (.a(A), .n(B[5:0]), .result(srl_result));  
    shift_sra sra_inst (.a(A), .n(B[5:0]), .result(sra_result));  
   
bit64_adder addr_adder_inst (
    .a($unsigned(A)), 
    .b({{52{addr[11]}}, addr}), 
    .sum(address),
    .carry(carry_out),
    .overflow(overflow_flag)
);
    bit64_adder addr_adderimm_inst (
        .a(A), 
        .b({{52{addr[11]}}, addr}), 
        .sum(addressi),
        .carry(carry_outi),
        .overflow(overflow_flagi)
    );

    bit64_subtractor beq_inst (.a(A), .b(B), .difference(sub_result), .borrow(sub_borrow),.overflow(sub_overflow));

    


   
    always @(*) begin
        
        case ({opcode, funct3, funct7})
           //ADD
            {7'b0110011, 3'b000, 7'b0000000}:begin
                result <= add_result;
                carry_alu <= add_carry;
                overflow_alu <= add_overflow;
                zero_flag <= 1'bx;

            end
           // SUB   
            {7'b0110011, 3'b000, 7'b0100000}: begin
                result <= sub_result;
                carry_alu <= sub_borrow;
                overflow_alu <= sub_overflow;
                zero_flag <= 1'bx;

               // if (sub_result == 64'd0) 
                  //  zero_flag <= 1'b1;
            end
            {7'b0110011, 3'b001, 7'b0000000}:  // SLL  
            begin
                result <= sll_result;
                carry_alu <= 1'bx;
                overflow_alu <= 1'bx;
                zero_flag <= 1'bx;

            end 

            {7'b0110011, 3'b010, 7'b0000000}: begin   // SLT
            
                result <= slt_result;
                carry_alu <= 1'bx;
                overflow_alu <= 1'bx;
                zero_flag <= 1'bx;

            end 
            {7'b0110011, 3'b011, 7'b0000000}:// SLTU
            begin
                result <= sltu_result;
                carry_alu <= 1'bx;
                overflow_alu <= 1'bx;

            end 
            {7'b0110011, 3'b100, 7'b0000000}:   // XOR
            begin
                result <= xor_result;
                carry_alu <= 1'bx;
                overflow_alu <= 1'bx;
                zero_flag <= 1'bx;

            end
            {7'b0110011, 3'b101, 7'b0000000}:   // SRL
            begin
                result <= srl_result;
                carry_alu <= 1'bx;
                overflow_alu <= 1'bx;
            end 
            {7'b0110011, 3'b101, 7'b0100000}:  // SRA
            begin
                result <= sra_result;
                carry_alu <= 1'bx;
                overflow_alu <= 1'bx;
                zero_flag <= 1'bx;
            end 
          
            {7'b0110011, 3'b111, 7'b0000000}:  // AND
            begin
                result <= and_result;
                carry_alu <= 1'bx;
                overflow_alu <= 1'bx;
                zero_flag <= 1'bx;
            end 
            {7'b0110011, 3'b110, 7'b0000000}:  // OR    
            begin
                result <= or_result;
                carry_alu <= 1'bx;
                overflow_alu <= 1'bx;
                zero_flag <= 1'bx;
            end

            {7'b0000011, 3'b011, 7'b0000000}:  // LOAD   (add)
            begin
                result <= address;
                zero_flag <= 1'bx;
                carry_alu <= 1'bx;
                overflow_alu <= 1'bx;

            end 

            {7'b0100011, 3'b011, 7'b0000000}:  // store  
            begin
                result <= address;
                zero_flag <= 1'bx;
                carry_alu <= 1'bx;
                overflow_alu <= 1'bx;
            end

            {7'b1100011, 3'b000, 7'b0000000}: //Beq
            begin
                result <= 64'bx;
                carry_alu <= 1'bx;
                overflow_alu <= 1'bx;
                
                if (sub_result == 64'd0) 
                    zero_flag <= 1'b1; 
                else 
                    zero_flag <= 1'b0;
               
                  
            end

            {7'b0010011, 3'b000, 7'b0000000}:  // addi   (add)
            begin
                result <= addressi;
                zero_flag <= 1'bx;

            end 


            

             default: // DEFAULT CASE
            begin
                result <= 64'hx;
                carry_alu <= 1'bx;
                overflow_alu <= 1'bx;
                zero_flag <= 1'bx;
            end 
        endcase
    end

endmodule

pipelined/pipeline_memory.v
`timescale 1ns / 1ps
//`include "alu.v"

module pipe_mem (
    input signed [63:0] rs1,        // Base register address
    input signed [63:0] rs2,        // Store value register
    input [6:0] op,                 // Operation opcode
    input [6:0] f7,                 // Funct7 field
    input [2:0] f3,                 // Function code (load/store type)
    input [11:0] imm12,             // 12-bit immediate offset
    input clk,                      // Clock signal
    input memread,                  // Memory read enable
    input memwrite,                 // Memory write enable
    input mem2reg,   
    input [63:0] addr,            // Memory to register control
    input [63:0] alures,       

    
         
    output reg [63:0] rd,           // Destination register (loaded value)
    output reg address_error        // Address out of bounds flag
);
    
    // Address calculation wire
    // wire [63:0] addr;
    wire carry_out, overflow_flag;

    // Use ALU to calculate memory address 
    // ALU address_calc (
    //     .funct7(f7),
    //     .funct3(f3),
    //     .opcode(op),
    //     .A(rs1),
    //     .B({{52{imm12[11]}}, imm12}),  // Sign-extend immediate
    //     .addr(imm12),
    //     .result(addr),
    //     .carry_alu(carry_out),
    //     .overflow_alu(overflow_flag)
    // );
    
    // bit64_adder add_instin(
    //     .a(rs1),
    //     .b({{52{imm12[11]}}, imm12}),
    //     .sum(addr),
    //     .carry(carry_out),
    //     .overflow(overflow_flag)
    // );


    // Memory with 1024 entries for 64-bit doublewords
    reg [63:0] memory [0:1023];
    
    // Memory initialization - Avoids truncation warnings
    integer i;
    initial begin
        for (i = 0; i < 1024; i = i + 1) begin
            memory[i] = 64'h0000000000000000;  // Ensure width consistency
        end
    end

    // Explicit 12-bit address extraction with masking to ensure correct range
    wire [11:0] word_addr = addr[11:0] & 12'hFFF; // Ensure only valid range is used

    // Memory access logic for SD and LD instructions
    always @(posedge clk) begin
        // Address boundary check
        if (word_addr > 12'hFFF) begin  // Ensure within 0 - 1023
            address_error <= 1'b1;  // Out of bounds
            rd <= 64'hX;            // Invalid data
        end else begin
            address_error <= 1'b0;
            
            // STORE Doubleword (SD) Operation
            if (memwrite && f3 == 3'b011) begin
                memory[word_addr] <= rs2;
                // $display("SD: Store Doubleword - Addr=%h, Value=%h", addr, rs2);
            end
            
            // LOAD Doubleword (LD) Operation
            if (memread && f3 == 3'b011) begin
                rd <= memory[word_addr];
                // $display("LD: Load Doubleword - Addr=%h, Value=%h", addr, memory[word_addr]);
            end

        end
    end

endmodule

sequential/seq/memory_tb.v
`timescale 1ns / 1ps

module riscv_ld_sd_tb();
    // Inputs
    reg clk;
    reg reset;
    
    // Signals for load/store testing
    reg [63:0] rs1;       // Base address register
    reg [63:0] rs2;       // Source/destination register
    reg [6:0] op;         // Opcode
    reg [6:0] f7;         // Funct7
    reg [2:0] f3;         // Funct3
    reg [11:0] imm12;     // Immediate offset
    reg memread;
    reg [63:0] addr;
    reg memwrite;
    reg mem2reg;
    reg [63:0] alures;    // Effective address

    // Outputs
    wire [63:0] rd;
    wire address_error;

    // Instantiate the Unit Under Test (UUT)
    pipe_mem uut (
        .rs1(rs1),
        .rs2(rs2),
        .op(op),
        .f7(f7),
        .f3(f3),
        .imm12(imm12),
        .clk(clk),
        .memread(memread),
        .addr(addr),
        .memwrite(memwrite),
        .mem2reg(mem2reg),
        .alures(alures),
        .rd(rd),
        .address_error(address_error)
    );

    // Clock generation
    always #5 clk = ~clk;

    // Test sequence
    initial begin
        // Initialize Inputs
        clk = 0;
        reset = 0;
        rs1 = 0;
        rs2 = 0;
        op = 0;
        f7 = 0;
        f3 = 0;
        imm12 = 0;
        memread = 0;
        memwrite = 0;
        mem2reg = 0;
        alures = 0; 
        addr = 0;

        // Wait 100 ns for global reset
        #100;

        // Test Case 1: Store Multiple Values
        $display("\n--- TEST CASE 1: STORE OPERATIONS ---");
        
        // First Store Operation (64-bit Double Word)
        op = 7'b0100011;  // Store type instruction (SD)
        f3 = 3'b011;      // Double word store
        f7 = 7'b0000000;
        
        // Store first value
        rs1 = 64'd13;  // Base address
        rs2 = 64'd11;  // Value to store
        imm12 = 12'd2;    
        addr = 64'd15;            // Offset
        
        // Explicitly calculate effective address
        alures = rs1 + {{52{imm12[11]}}, imm12};
        
        memwrite = 1;
        memread = 0;
        $display("Store 1: Address = %d, Value = %0h", addr, rs2);
        #10;

        // Second Store Operation
        rs1 = 64'h0000_0000_0000_2000;  // New base address
        rs2 = 64'hABCD_1234_5678_9ABC;  // Another value to store
        imm12 = 12'h008;   
        addr = 64'd8;                 // Different offset
        
        // Explicitly calculate effective address
        alures = rs1 + {{52{imm12[11]}}, imm12};
        
        $display("Store 2: Address = %d, Value = %0h", addr, rs2);
        #10;
        memwrite = 0;

        // Test Case 2: Load Stored Values
        $display("\n--- TEST CASE 2: LOAD OPERATIONS ---");
        
        // Prepare for first load
        op = 7'b0000011;  // Load type instruction (LD)
        f3 = 3'b011;      // Double word load
        memread = 1;
        memwrite = 0;
        
        // First Load Operation
        rs1 = 64'h0000_0000_0000_1000;  // Base address
        imm12 = 12'h004; 
        addr = 64'd4; 
                       // Offset
        
        // Explicitly calculate effective address
        alures = rs1 + {{52{imm12[11]}}, imm12};
        
        $display("Load 1: Address = %0h", addr);
        #10;
        $display("Loaded Value 1: %0h", rd);

        // Second Load Operation
        rs1 = 64'h0000_0000_0000_2000;  // New base address
        imm12 = 12'h008; 
        addr = 64'd8;                // Different offset
        
        // Explicitly calculate effective address
        alures = rs1 + {{52{imm12[11]}}, imm12};
        
        $display("Load 2: Address = %0h", addr);
        #10;
        $display("Loaded Value 2: %0h", rd);

        // Finish simulation
        #10 $finish;
    end

    // Optional: Waveform dump for GTKWave
    initial begin
        $dumpfile("riscv_ld_sd_tb.vcd");
        $dumpvars(0, riscv_ld_sd_tb);
    end
endmodule

pipelined/riscv_ld_sd_tb.vcd
$date
	Mon Mar 10 22:56:08 2025
$end
$version
	Icarus Verilog
$end
$timescale
	1ps
$end
$scope module riscv_ld_sd_tb $end
$var wire 64 ! rd [63:0] $end
$var wire 1 " address_error $end
$var reg 64 # addr [63:0] $end
$var reg 64 $ alures [63:0] $end
$var reg 1 % clk $end
$var reg 3 & f3 [2:0] $end
$var reg 7 ' f7 [6:0] $end
$var reg 12 ( imm12 [11:0] $end
$var reg 1 ) mem2reg $end
$var reg 1 * memread $end
$var reg 1 + memwrite $end
$var reg 7 , op [6:0] $end
$var reg 1 - reset $end
$var reg 64 . rs1 [63:0] $end
$var reg 64 / rs2 [63:0] $end
$scope module uut $end
$var wire 64 0 addr [63:0] $end
$var wire 64 1 alures [63:0] $end
$var wire 1 % clk $end
$var wire 3 2 f3 [2:0] $end
$var wire 7 3 f7 [6:0] $end
$var wire 12 4 imm12 [11:0] $end
$var wire 1 ) mem2reg $end
$var wire 1 * memread $end
$var wire 1 + memwrite $end
$var wire 7 5 op [6:0] $end
$var wire 64 6 rs1 [63:0] $end
$var wire 64 7 rs2 [63:0] $end
$var wire 12 8 word_addr [11:0] $end
$var reg 1 " address_error $end
$var reg 64 9 rd [63:0] $end
$var integer 32 : i [31:0] $end
$upscope $end
$upscope $end
$enddefinitions $end
#0
$dumpvars
b10000000000 :
bx 9
b0 8
b0 7
b0 6
b0 5
b0 4
b0 3
b0 2
b0 1
b0 0
b0 /
b0 .
0-
b0 ,
0+
0*
0)
b0 (
b0 '
b0 &
0%
b0 $
b0 #
x"
bx !
$end
#5000
0"
1%
#10000
0%
#15000
1%
#20000
0%
#25000
1%
#30000
0%
#35000
1%
#40000
0%
#45000
1%
#50000
0%
#55000
1%
#60000
0%
#65000
1%
#70000
0%
#75000
1%
#80000
0%
#85000
1%
#90000
0%
#95000
1%
#100000
b100 8
0%
1+
b1000000000100 $
b1000000000100 1
b100 #
b100 0
b100 (
b100 4
b1000100010001001000100010001000110011001100110100010001000100 /
b1000100010001001000100010001000110011001100110100010001000100 7
b1000000000000 .
b1000000000000 6
b11 &
b11 2
b100011 ,
b100011 5
#105000
1%
#110000
b1000 8
0%
b10000000001000 $
b10000000001000 1
b1000 #
b1000 0
b1000 (
b1000 4
b1010101111001101000100100011010001010110011110001001101010111100 /
b1010101111001101000100100011010001010110011110001001101010111100 7
b10000000000000 .
b10000000000000 6
#115000
1%
#120000
b100 8
0%
b1000000000100 $
b1000000000100 1
b100 #
b100 0
b100 (
b100 4
b1000000000000 .
b1000000000000 6
1*
b11 ,
b11 5
0+
#125000
b1000100010001001000100010001000110011001100110100010001000100 !
b1000100010001001000100010001000110011001100110100010001000100 9
1%
#130000
b1000 8
0%
b10000000001000 $
b10000000001000 1
b1000 #
b1000 0
b1000 (
b1000 4
b10000000000000 .
b10000000000000 6
#135000
b1010101111001101000100100011010001010110011110001001101010111100 !
b1010101111001101000100100011010001010110011110001001101010111100 9
1%
